LICENSE-apl
LICENSE-mpl
README.md
pyeigenisolve.cpp
pyeigenisolve.py
setup.py
pyeigenisolve.egg-info/PKG-INFO
pyeigenisolve.egg-info/SOURCES.txt
pyeigenisolve.egg-info/dependency_links.txt
pyeigenisolve.egg-info/top_level.txteigen-3.4.0
eigen-3.4.0/.hgeol
eigen-3.4.0/COPYING.LGPL
eigen-3.4.0/blas
eigen-3.4.0/blas/single.cpp
eigen-3.4.0/blas/level1_cplx_impl.h
eigen-3.4.0/blas/CMakeLists.txt
eigen-3.4.0/blas/level2_real_impl.h
eigen-3.4.0/blas/level1_real_impl.h
eigen-3.4.0/blas/GeneralRank1Update.h
eigen-3.4.0/blas/complex_single.cpp
eigen-3.4.0/blas/level2_impl.h
eigen-3.4.0/blas/level2_cplx_impl.h
eigen-3.4.0/blas/PackedTriangularSolverVector.h
eigen-3.4.0/blas/f2c
eigen-3.4.0/blas/f2c/ctbmv.c
eigen-3.4.0/blas/f2c/dsbmv.c
eigen-3.4.0/blas/f2c/ztbmv.c
eigen-3.4.0/blas/f2c/dspmv.c
eigen-3.4.0/blas/f2c/lsame.c
eigen-3.4.0/blas/f2c/drotmg.c
eigen-3.4.0/blas/f2c/srotm.c
eigen-3.4.0/blas/f2c/dtbmv.c
eigen-3.4.0/blas/f2c/chpmv.c
eigen-3.4.0/blas/f2c/datatypes.h
eigen-3.4.0/blas/f2c/stbmv.c
eigen-3.4.0/blas/f2c/drotm.c
eigen-3.4.0/blas/f2c/zhpmv.c
eigen-3.4.0/blas/f2c/zhbmv.c
eigen-3.4.0/blas/f2c/chbmv.c
eigen-3.4.0/blas/f2c/r_cnjg.c
eigen-3.4.0/blas/f2c/sspmv.c
eigen-3.4.0/blas/f2c/ssbmv.c
eigen-3.4.0/blas/f2c/complexdots.c
eigen-3.4.0/blas/f2c/srotmg.c
eigen-3.4.0/blas/f2c/d_cnjg.c
eigen-3.4.0/blas/testing
eigen-3.4.0/blas/testing/zblat2.dat
eigen-3.4.0/blas/testing/zblat3.dat
eigen-3.4.0/blas/testing/sblat3.f
eigen-3.4.0/blas/testing/zblat2.f
eigen-3.4.0/blas/testing/CMakeLists.txt
eigen-3.4.0/blas/testing/dblat3.dat
eigen-3.4.0/blas/testing/dblat2.dat
eigen-3.4.0/blas/testing/dblat1.f
eigen-3.4.0/blas/testing/runblastest.sh
eigen-3.4.0/blas/testing/cblat3.dat
eigen-3.4.0/blas/testing/cblat2.dat
eigen-3.4.0/blas/testing/zblat1.f
eigen-3.4.0/blas/testing/cblat3.f
eigen-3.4.0/blas/testing/dblat2.f
eigen-3.4.0/blas/testing/sblat1.f
eigen-3.4.0/blas/testing/sblat2.dat
eigen-3.4.0/blas/testing/sblat3.dat
eigen-3.4.0/blas/testing/dblat3.f
eigen-3.4.0/blas/testing/cblat2.f
eigen-3.4.0/blas/testing/sblat2.f
eigen-3.4.0/blas/testing/zblat3.f
eigen-3.4.0/blas/testing/cblat1.f
eigen-3.4.0/blas/common.h
