Metadata-Version: 2.1
Name: pyeigenisolve
Version: 1.0.1
Summary: Sparse matrix iterative solvers with Eigen
Home-page: https://github.com/drorspei/pyeigenisolve
Author: dror
Author-email: dror.mastershin@gmail.com
License: UNKNOWN
Platform: UNKNOWN
Classifier: Programming Language :: Python :: 3
Classifier: License :: OSI Approved :: Mozilla Public License 2.0 (MPL 2.0)
Classifier: License :: OSI Approved :: Apache Software License
Classifier: Operating System :: OS Independent
License-File: LICENSE-apl
License-File: LICENSE-mpl
